etb_env/Env.py
etb_env/__init__.py
etb_env-0.2.1.dist-info/LICENSE
etb_env-0.2.1.dist-info/WHEEL
etb_env-0.2.1.dist-info/METADATA
etb_env-0.2.1.dist-info/RECORD
