Metadata-Version: 2.1
Name: etb-env
Version: 0.2.1
Summary: A little class for getting env variables
License: MIT
Author: Tate Button
Author-email: yg3bpwn0or679hau8fxi@duck.com
Requires-Python: >=3.10,<4.0
Classifier: License :: OSI Approved :: MIT License
Classifier: Programming Language :: Python :: 3
Classifier: Programming Language :: Python :: 3.10
Requires-Dist: python-dotenv (>=1.0.0,<2.0.0)
